visionbrowser/__init__.py
visionbrowser/api.py
visionbrowser/endpoints.py
visionbrowser/exceptions.py
visionbrowser-0.0.3.dist-info/METADATA
visionbrowser-0.0.3.dist-info/WHEEL
visionbrowser-0.0.3.dist-info/top_level.txt
visionbrowser-0.0.3.dist-info/RECORD
