Metadata-Version: 2.1
Name: visionbrowser
Version: 0.0.3
Summary: Async API wrapper for Vision Browser
Author: europecdc
Author-email: europecdc@hotmail.com
Keywords: python,undetected-browser,browser,vision,visionbrowser,api,wrapper
Classifier: Development Status :: 4 - Beta
Classifier: Intended Audience :: Developers
Classifier: Programming Language :: Python :: 3
Classifier: Operating System :: Unix
Classifier: Operating System :: MacOS :: MacOS X
Classifier: Operating System :: Microsoft :: Windows
Requires-Dist: aiohttp
Requires-Dist: aiosignal
Requires-Dist: attrs
Requires-Dist: frozenlist
Requires-Dist: idna
Requires-Dist: multidict
Requires-Dist: yarl
